vcs2l/__init__.py
vcs2l/crawler.py
vcs2l/errors.py
vcs2l/executor.py
vcs2l/streams.py
vcs2l/util.py
vcs2l/clients/__init__.py
vcs2l/clients/bzr.py
vcs2l/clients/git.py
vcs2l/clients/hg.py
vcs2l/clients/none.py
vcs2l/clients/svn.py
vcs2l/clients/tar.py
vcs2l/clients/vcs_base.py
vcs2l/clients/zip.py
vcs2l/commands/__init__.py
vcs2l/commands/branch.py
vcs2l/commands/command.py
vcs2l/commands/custom.py
vcs2l/commands/delete.py
vcs2l/commands/diff.py
vcs2l/commands/export.py
vcs2l/commands/help.py
vcs2l/commands/import_.py
vcs2l/commands/log.py
vcs2l/commands/pull.py
vcs2l/commands/push.py
vcs2l/commands/remotes.py
vcs2l/commands/status.py
vcs2l/commands/validate.py
vcs2l/commands/vcs.py
vcs2l-1.1.5.data/data/share/vcs2l-completion/vcs.bash
vcs2l-1.1.5.data/data/share/vcs2l-completion/vcs.fish
vcs2l-1.1.5.data/data/share/vcs2l-completion/vcs.tcsh
vcs2l-1.1.5.data/data/share/vcs2l-completion/vcs.zsh
vcs2l-1.1.5.dist-info/LICENSE
vcs2l-1.1.5.dist-info/METADATA
vcs2l-1.1.5.dist-info/WHEEL
vcs2l-1.1.5.dist-info/entry_points.txt
vcs2l-1.1.5.dist-info/top_level.txt
vcs2l-1.1.5.dist-info/RECORD
