Metadata-Version: 2.1
Name: vcs2l
Version: 1.1.5
Summary: vcs2l provides a command line tool to invoke vcs commands on multiple repositories.
Home-page: https://github.com/ros-infrastructure/vcs2l
Author: Dirk Thomas
Author-email: web@dirk-thomas.net
Maintainer: ROS Infrastructure Team
License: Apache-2.0
Project-URL: Source code, https://github.com/ros-infrastructure/vcs2l
Project-URL: Issue tracker, https://github.com/ros-infrastructure/vcs2l/issues
Keywords: vcs,version control,git,hg,svn,bzr
Platform: UNKNOWN
Classifier: Development Status :: 5 - Production/Stable
Classifier: Intended Audience :: Developers
Classifier: Programming Language :: Python
Classifier: Topic :: Software Development :: Version Control
Classifier: Topic :: Utilities
License-File: LICENSE
Requires-Dist: PyYAML
Requires-Dist: setuptools ; python_version < "3.7"
Requires-Dist: importlib-metadata ; python_version < "3.8" and python_version >= "3.7"
Provides-Extra: docs
Requires-Dist: sphinx (>=8.2) ; extra == 'docs'
Requires-Dist: sphinx-rtd-theme ; extra == 'docs'
Provides-Extra: test
Requires-Dist: pytest ; extra == 'test'
